EmbedOMIM
